givernylocal/__init__.py
givernylocal/turbulence_dataset.py
givernylocal/turbulence_gizmos/__init__.py
givernylocal/turbulence_gizmos/basic_gizmos.py
givernylocal/turbulence_gizmos/constants.py
givernylocal/turbulence_gizmos/jhtdb_schema.py
givernylocal/turbulence_gizmos/variable_dy_grid_ys.py
givernylocal/turbulence_gizmos/variable_grids.py
givernylocal/turbulence_toolkit.py
givernylocal-3.5.2.dist-info/METADATA
givernylocal-3.5.2.dist-info/WHEEL
givernylocal-3.5.2.dist-info/licenses/LICENSE.txt
givernylocal-3.5.2.dist-info/RECORD
